README.md
setup.py
taskseq.py
taskseq.egg-info/PKG-INFO
taskseq.egg-info/SOURCES.txt
taskseq.egg-info/dependency_links.txt
taskseq.egg-info/entry_points.txt
taskseq.egg-info/requires.txt
taskseq.egg-info/top_level.txt