Metadata-Version: 2.1
Name: taskseq
Version: 0.1.0
Summary: Script to quickly sequence taskwarrior tasks
Home-page: https://github.com/voidcase/{NAME}
Author: Isak Lindhé
Author-email: isak.e.lindhe@gmail.com
License: MIT
Download-URL: https://github.com/voidcase/taskseq/archive/v0.1.0.tar.gz
Platform: UNKNOWN
Classifier: Programming Language :: Python :: 3
Classifier: Environment :: Console
Classifier: License :: OSI Approved :: GNU General Public License v3 or later (GPLv3+)
Classifier: Operating System :: POSIX
Classifier: Operating System :: MacOS
Requires-Python: >=3.6
